subscribie_cli/__init__.py
subscribie_cli/cli.py
subscribiecli-0.0.96.dist-info/METADATA
subscribiecli-0.0.96.dist-info/WHEEL
subscribiecli-0.0.96.dist-info/entry_points.txt
subscribiecli-0.0.96.dist-info/top_level.txt
subscribiecli-0.0.96.dist-info/RECORD
