Metadata-Version: 2.1
Name: subscribiecli
Version: 0.0.96
Summary: UNKNOWN
Home-page: UNKNOWN
Author: Karma Computing
Author-email: subscribie@karmacomputing.co.uk
License: UNKNOWN
Platform: UNKNOWN
Classifier: Programming Language :: Python :: 3
Classifier: License :: OSI Approved :: GNU Affero General Public License v3
Classifier: Operating System :: OS Independent
Requires-Python: >=3
Requires-Dist: click
Requires-Dist: gitpython
Requires-Dist: pyOpenSSL
